bogging/__init__.py
bogging/config.py
bogging/handlers.py
bogging-1.0.0.dist-info/METADATA
bogging-1.0.0.dist-info/WHEEL
bogging-1.0.0.dist-info/top_level.txt
bogging-1.0.0.dist-info/RECORD
